copilot_money/__init__.py
copilot_money/api.py
copilot_money/cli.py
copilot_money/config.py
copilot_money/models.py
copilot_money_cli-0.1.2.dist-info/METADATA
copilot_money_cli-0.1.2.dist-info/WHEEL
copilot_money_cli-0.1.2.dist-info/entry_points.txt
copilot_money_cli-0.1.2.dist-info/licenses/LICENSE
copilot_money_cli-0.1.2.dist-info/RECORD
