Metadata-Version: 2.4
Name: copilot-money-cli
Version: 0.1.2
Summary: CLI for Copilot Money personal finance
Project-URL: Homepage, https://github.com/jayhickey/copilot-money-cli
Project-URL: Repository, https://github.com/jayhickey/copilot-money-cli
License-Expression: MIT
License-File: LICENSE
Requires-Python: >=3.10
Requires-Dist: httpx==0.27.0
Requires-Dist: pydantic>=2.5.0
Requires-Dist: rich==13.7.1
Requires-Dist: typer>=0.15.0
Provides-Extra: dev
Requires-Dist: pytest>=7.0.0; extra == 'dev'
Requires-Dist: ruff>=0.1.0; extra == 'dev'
